vesselmodels/__init__.py
vesselmodels/init_3f.py
vesselmodels/init_pm.py
vesselmodels/parameters_vessel_1.py
vesselmodels/parameters_vessel_2.py
vesselmodels/parameters_vessel_3.py
vesselmodels/vessel_dynamics_3F.py
vesselmodels/vessel_dynamics_pm.py
vesselmodels/vessel_dynamics_vp.py
vesselmodels/vessel_dynamics_yp.py
vesselmodels/vessel_parameters.py
vesselmodels/utils/__init__.py
vesselmodels/utils/input_constraints.py
vesselmodels/utils/unitConversion.py
commonocean_vessel_models-1.0.0.dist-info/LICENSE.txt
commonocean_vessel_models-1.0.0.dist-info/METADATA
commonocean_vessel_models-1.0.0.dist-info/WHEEL
commonocean_vessel_models-1.0.0.dist-info/top_level.txt
commonocean_vessel_models-1.0.0.dist-info/RECORD
