Metadata-Version: 2.1
Name: commonocean-vessel-models
Version: 1.0.0
Summary: Implementation of vessels models with varying abstraction levels.
Home-page: https://commonocean.cps.cit.tum.de/
Author: Cyber-Physical Systems Group, Technical University of Munich
Author-email: commonocean@lists.lrz.de
Keywords: autonomous automated vessels motion planning
Classifier: Programming Language :: Python :: 3.7
Classifier: License :: OSI Approved :: BSD License
Classifier: Operating System :: POSIX :: Linux
Classifier: Operating System :: MacOS
License-File: LICENSE.txt
